setup.py
mytest123/Binomialdistribution.py
mytest123/Gaussiandistribution.py
mytest123/Generaldistribution.py
mytest123/__init__.py
testing123.egg-info/PKG-INFO
testing123.egg-info/SOURCES.txt
testing123.egg-info/dependency_links.txt
testing123.egg-info/not-zip-safe
testing123.egg-info/top_level.txt